fidesctl/__init__.py
fidesctl/_version.py
fidesctl/api/__init__.py
fidesctl/api/main.py
fidesctl/api/ctl/__init__.py
fidesctl/api/ctl/alembic.ini
fidesctl/api/ctl/deps.py
fidesctl/api/ctl/sql_models.py
fidesctl/api/ctl/ui.py
fidesctl/api/ctl/view.py
fidesctl/api/ctl/database/__init__.py
fidesctl/api/ctl/database/crud.py
fidesctl/api/ctl/database/database.py
fidesctl/api/ctl/database/session.py
fidesctl/api/ctl/migrations/__init__.py
fidesctl/api/ctl/migrations/env.py
fidesctl/api/ctl/migrations/versions/150f234ef1de_add_fidesctl_meta_to_organization_object.py
fidesctl/api/ctl/migrations/versions/155fd8e51d9d_add_fideslib_models.py
fidesctl/api/ctl/migrations/versions/1739aa4a4ab7_add_security_policy_link_and_erasure_.py
fidesctl/api/ctl/migrations/versions/26934c96ec80_initial_migration.py
fidesctl/api/ctl/migrations/versions/312aff72b275_migrate_to_usage_of_evaluation_.py
fidesctl/api/ctl/migrations/versions/327cd266f7b3_update_dataset_depth.py
fidesctl/api/ctl/migrations/versions/3d9c476d7cea_classification_management.py
fidesctl/api/ctl/migrations/versions/45c7a349db68_remove_qualifier_lists_from_data_set_.py
fidesctl/api/ctl/migrations/versions/4c3693c289d0_add_optional_contact_information_for_.py
fidesctl/api/ctl/migrations/versions/4fc34906c389_.py
fidesctl/api/ctl/migrations/versions/50b3736634d2_extend_data_use_with_recipients_and_.py
fidesctl/api/ctl/migrations/versions/6b9885e68cbb_add_plus_system_scans_table.py
fidesctl/api/ctl/migrations/versions/6bd93cb0603d_add_egress_and_ingress_to_systems.py
fidesctl/api/ctl/migrations/versions/732105cd54e3_update_dataset_field_name.py
fidesctl/api/ctl/migrations/versions/7a94527643a1_add_column_for_special_category_to_data_.py
fidesctl/api/ctl/migrations/versions/7c851d8a102a_add_created_at_and_updated_at.py
fidesctl/api/ctl/migrations/versions/__init__.py
fidesctl/api/ctl/migrations/versions/a2b9b156ebaf_data_protection_impact_assessments_.py
fidesctl-1.9.6.dist-info/LICENSE
fidesctl-1.9.6.dist-info/METADATA
fidesctl-1.9.6.dist-info/WHEEL
fidesctl-1.9.6.dist-info/entry_points.txt
fidesctl-1.9.6.dist-info/top_level.txt
fidesctl-1.9.6.dist-info/RECORD
