Metadata-Version: 2.1
Name: fidesctl
Version: 1.9.6
Summary: CLI for Fides
Home-page: https://github.com/ethyca/fides
Author: Ethyca, Inc.
Author-email: fidesteam@ethyca.com
License: Apache License 2.0
Classifier: License :: OSI Approved :: Apache Software License
Classifier: Programming Language :: Python :: 3 :: Only
Classifier: Programming Language :: Python :: 3.9
Classifier: Programming Language :: Python :: 3.10
Classifier: Topic :: Software Development :: Libraries
Requires-Python: >=3.9, <4
License-File: LICENSE
Requires-Dist: alembic (==1.8.0)
Requires-Dist: asyncpg (==0.25.0)
Requires-Dist: click (>=8.1)
Requires-Dist: colorama (>=0.4.3)
Requires-Dist: cryptography (>=36)
Requires-Dist: deepdiff (==5.8.0)
Requires-Dist: fastapi-pagination[sqlalchemy] (==0.9.3)
Requires-Dist: fastapi (==0.77.1)
Requires-Dist: fideslang (==1.3.1)
Requires-Dist: fideslib (==3.0.1)
Requires-Dist: fideslog (==1.1.5)
Requires-Dist: GitPython (==3.1)
Requires-Dist: loguru (<0.6,>=0.5)
Requires-Dist: openpyxl (==3.0.9)
Requires-Dist: pandas (==1.4)
Requires-Dist: plotly (==5.4)
Requires-Dist: psycopg2-binary (==2.9.1)
Requires-Dist: pydantic (<1.10.0,>=1.8.1)
Requires-Dist: PyJWT (==2.4.0)
Requires-Dist: pyyaml (<6,>=5)
Requires-Dist: requests (<3,>=2)
Requires-Dist: SQLAlchemy-Utils (==0.38.2)
Requires-Dist: sqlalchemy[asyncio] (==1.4.27)
Requires-Dist: toml (>=0.10.1)
Requires-Dist: uvicorn (==0.17.6)
Requires-Dist: versioneer (==0.19)
Provides-Extra: all
Requires-Dist: boto3 (==1.20.54) ; extra == 'all'
Requires-Dist: pymysql (==1.0.0) ; extra == 'all'
Requires-Dist: okta (==2.5.0) ; extra == 'all'
Requires-Dist: snowflake-sqlalchemy (==1.3.4) ; extra == 'all'
Requires-Dist: sqlalchemy-redshift (==0.8.8) ; extra == 'all'
Requires-Dist: sqlalchemy-bigquery (==1.4.4) ; extra == 'all'
Provides-Extra: aws
Requires-Dist: boto3 (==1.20.54) ; extra == 'aws'
Provides-Extra: bigquery
Requires-Dist: sqlalchemy-bigquery (==1.4.4) ; extra == 'bigquery'
Provides-Extra: mssql
Requires-Dist: pyodbc (==4.0.32) ; extra == 'mssql'
Provides-Extra: mysql
Requires-Dist: pymysql (==1.0.0) ; extra == 'mysql'
Provides-Extra: okta
Requires-Dist: okta (==2.5.0) ; extra == 'okta'
Provides-Extra: redshift
Requires-Dist: sqlalchemy-redshift (==0.8.8) ; extra == 'redshift'
Provides-Extra: snowflake
Requires-Dist: snowflake-sqlalchemy (==1.3.4) ; extra == 'snowflake'
